logseq_to_obsidian/__init__.py
logseq_to_obsidian/__main__.py
logseq_to_obsidian/cli.py
logseq_to_obsidian/planner.py
logseq_to_obsidian/transformer.py
logseq_to_obsidian/version.py
logseq_to_obsidian-0.1.2.dist-info/METADATA
logseq_to_obsidian-0.1.2.dist-info/WHEEL
logseq_to_obsidian-0.1.2.dist-info/entry_points.txt
logseq_to_obsidian-0.1.2.dist-info/licenses/LICENSE
logseq_to_obsidian-0.1.2.dist-info/RECORD
