Metadata-Version: 2.4
Name: logseq-to-obsidian
Version: 0.1.2
Summary: Convert a Logseq vault to Obsidian-friendly Markdown
License-Expression: MIT
License-File: LICENSE
Author: Georg Lutz
Author-email: georg@georglutz.de
Requires-Python: >=3.9,<4.0
Classifier: Development Status :: 5 - Production/Stable
Classifier: License :: OSI Approved :: MIT License
Classifier: Operating System :: OS Independent
Classifier: Environment :: Console
Classifier: Programming Language :: Python
Classifier: Programming Language :: Python :: 3
Classifier: Programming Language :: Python :: 3.9
Classifier: Programming Language :: Python :: 3.10
Classifier: Programming Language :: Python :: 3.11
Classifier: Programming Language :: Python :: 3.12
Classifier: Topic :: Text Processing :: Markup :: Markdown
Classifier: Topic :: Utilities
Project-URL: Homepage, https://github.com/sercxanto/logseq-to-obsidian
Project-URL: Repository, https://github.com/sercxanto/logseq-to-obsidian.git
